lib/__init__.py
lib/scanner.py
scannertesting-1.0.0.dist-info/METADATA
scannertesting-1.0.0.dist-info/WHEEL
scannertesting-1.0.0.dist-info/top_level.txt
scannertesting-1.0.0.dist-info/RECORD
